multigen/__init__.py
multigen/backends/__init__.py
multigen/backends/base.py
multigen/backends/base_converter.py
multigen/backends/c/__init__.py
multigen/backends/c/backend.py
multigen/backends/c/builder.py
multigen/backends/c/container_codegen.py
multigen/backends/c/containers.py
multigen/backends/c/converter.py
multigen/backends/c/emitter.py
multigen/backends/c/enhanced_type_inference.py
multigen/backends/c/ext/__init__.py
multigen/backends/c/ext/stc/LICENSE
multigen/backends/c/ext/stc/README.md
multigen/backends/c/ext/stc/__init__.py
multigen/backends/c/ext/stc/allocators.py
multigen/backends/c/ext/stc/containers.py
multigen/backends/c/ext/stc/enhanced_memory_manager.py
multigen/backends/c/ext/stc/enhanced_translator.py
multigen/backends/c/ext/stc/enhanced_type_inference.py
multigen/backends/c/ext/stc/include/c11/fmt.h
multigen/backends/c/ext/stc/include/stc/algorithm.h
multigen/backends/c/ext/stc/include/stc/arc.h
multigen/backends/c/ext/stc/include/stc/box.h
multigen/backends/c/ext/stc/include/stc/cbits.h
multigen/backends/c/ext/stc/include/stc/common.h
multigen/backends/c/ext/stc/include/stc/coption.h
multigen/backends/c/ext/stc/include/stc/coroutine.h
multigen/backends/c/ext/stc/include/stc/cregex.h
multigen/backends/c/ext/stc/include/stc/cspan.h
multigen/backends/c/ext/stc/include/stc/cstr.h
multigen/backends/c/ext/stc/include/stc/csview.h
multigen/backends/c/ext/stc/include/stc/deque.h
multigen/backends/c/ext/stc/include/stc/hashmap.h
multigen/backends/c/ext/stc/include/stc/hashset.h
multigen/backends/c/ext/stc/include/stc/hmap.h
multigen/backends/c/ext/stc/include/stc/hset.h
multigen/backends/c/ext/stc/include/stc/list.h
multigen/backends/c/ext/stc/include/stc/pqueue.h
multigen/backends/c/ext/stc/include/stc/priv/cregex_prv.c
multigen/backends/c/ext/stc/include/stc/priv/cstr_prv.c
multigen/backends/c/ext/stc/include/stc/priv/cstr_prv.h
multigen/backends/c/ext/stc/include/stc/priv/linkage.h
multigen/backends/c/ext/stc/include/stc/priv/linkage2.h
multigen-0.1.113.dist-info/licenses/LICENSE
multigen-0.1.113.dist-info/WHEEL
multigen-0.1.113.dist-info/entry_points.txt
multigen-0.1.113.dist-info/METADATA
multigen-0.1.113.dist-info/RECORD
