Metadata-Version: 2.4
Name: multigen
Version: 0.1.113
Summary: Python-to-Many code translation
Keywords: code-generation,compiler,metaprogramming
Author: Shakeeb Alireza
Author-email: Shakeeb Alireza <shakfu@users.noreply.github.com>
License-Expression: MIT
License-File: LICENSE
Classifier: Development Status :: 4 - Beta
Classifier: Intended Audience :: Developers
Classifier: License :: OSI Approved :: MIT License
Classifier: Operating System :: OS Independent
Classifier: Programming Language :: Python :: 3
Classifier: Programming Language :: Python :: 3.9
Classifier: Programming Language :: Python :: 3.10
Classifier: Programming Language :: Python :: 3.11
Classifier: Programming Language :: Python :: 3.12
Classifier: Programming Language :: Python :: 3.13
Classifier: Topic :: Software Development :: Code Generators
Classifier: Topic :: Software Development :: Compilers
Requires-Dist: llvmlite>=0.43.0 ; extra == 'all'
Requires-Dist: z3-solver>=4.13.0 ; extra == 'all'
Requires-Dist: llvmlite>=0.43.0 ; extra == 'llvm'
Requires-Dist: z3-solver>=4.13.0 ; extra == 'verification'
Requires-Dist: z3-solver>=4.13.0 ; extra == 'z3'
Requires-Python: >=3.9
Project-URL: Bug Tracker, https://github.com/shakfu/multigen/issues
Project-URL: Documentation, https://multigen.readthedocs.io
Project-URL: Homepage, https://github.com/shakfu/multigen
Project-URL: Repository, https://github.com/shakfu/multigen
Provides-Extra: all
Provides-Extra: llvm
Provides-Extra: verification
Provides-Extra: z3
